lastfmxpy/__init__.py
lastfmxpy/api.py
lastfmxpy/config.py
lastfmxpy/exeptions.py
lastfmxpy/literals.py
lastfmxpy/unions.py
lastfmxpy/utils.py
lastfmxpy/methods/__init__.py
lastfmxpy/methods/album.py
lastfmxpy/methods/artist.py
lastfmxpy/methods/auth.py
lastfmxpy/methods/chart.py
lastfmxpy/methods/geo.py
lastfmxpy/methods/library.py
lastfmxpy/methods/tag.py
lastfmxpy/methods/track.py
lastfmxpy/methods/user.py
lastfmxpy/params/__init__.py
lastfmxpy/params/album_params.py
lastfmxpy/params/artist_params.py
lastfmxpy/params/auth_params.py
lastfmxpy/params/base_classes.py
lastfmxpy/params/chart_params.py
lastfmxpy/params/geo_params.py
lastfmxpy/params/library_params.py
lastfmxpy/params/tag_params.py
lastfmxpy/params/track_params.py
lastfmxpy/params/user_params.py
lastfmxpy-1.2.2.dist-info/LICENCE
lastfmxpy-1.2.2.dist-info/METADATA
lastfmxpy-1.2.2.dist-info/WHEEL
lastfmxpy-1.2.2.dist-info/top_level.txt
lastfmxpy-1.2.2.dist-info/RECORD
