Metadata-Version: 2.1
Name: lastfmxpy
Version: 1.2.2
Summary: A tool that helps to work effectively with the API from last.fm
Home-page: https://github.com/pkeorley/lastfmxpy
Author: pkeorley
Author-email: pkeorley@gmail.com
License: MIT
Requires-Python: >=3.10
License-File: LICENCE
Requires-Dist: requests >=2.31.0
Requires-Dist: aiohttp ~=3.8.4
